knf_predictor/__init__.py
knf_predictor/cli.py
knf_predictor/graph_builder.py
knf_predictor/models.py
knf_predictor/predictor.py
knf_predictor/data/KNF_Ensemble_v1.0.pth
knf_predictor-2.0.1.dist-info/licenses/License
knf_predictor-2.0.1.dist-info/METADATA
knf_predictor-2.0.1.dist-info/WHEEL
knf_predictor-2.0.1.dist-info/entry_points.txt
knf_predictor-2.0.1.dist-info/top_level.txt
knf_predictor-2.0.1.dist-info/RECORD
