Metadata-Version: 2.4
Name: knf-predictor
Version: 2.0.1
Summary: Ultra-fast prediction of supramolecular stability using Graph Neural Networks
Home-page: https://github.com/prasanna-kulkarni/knf-predictor
Author: Prasanna P. Kulkarni
Author-email: "Prasanna P. Kulkarni" <prasannakulkarni163@gmail.com>
License: MIT
Project-URL: Homepage, https://github.com/Prasanna163/KNF-Predictor
Project-URL: Documentation, https://github.com/Prasanna163/KNF-Predictor#readme
Project-URL: Repository, https://github.com/Prasanna163/KNF-Predictor.git
Project-URL: Issues, https://github.com/Prasanna163/KNF-Predictor/issues
Project-URL: Changelog, https://github.com/Prasanna163/KNF-Predictor/releases
Keywords: chemistry,machine-learning,supramolecular,deep-learning,graph-neural-networks,cheminformatics
Classifier: Development Status :: 4 - Beta
Classifier: Intended Audience :: Science/Research
Classifier: License :: OSI Approved :: MIT License
Classifier: Programming Language :: Python :: 3.8
Classifier: Programming Language :: Python :: 3.9
Classifier: Programming Language :: Python :: 3.10
Classifier: Programming Language :: Python :: 3.11
Classifier: Topic :: Scientific/Engineering :: Chemistry
Classifier: Topic :: Scientific/Engineering :: Artificial Intelligence
Requires-Python: >=3.8
License-File: License
Requires-Dist: torch>=2.0.0
Requires-Dist: torch-geometric>=2.3.0
Requires-Dist: numpy>=1.24.0
Requires-Dist: pandas>=2.0.0
Requires-Dist: scikit-learn>=1.3.0
Requires-Dist: tqdm>=4.65.0
Provides-Extra: dev
Requires-Dist: pytest>=7.0; extra == "dev"
Requires-Dist: black>=22.0; extra == "dev"
Requires-Dist: flake8>=5.0; extra == "dev"
Dynamic: author
Dynamic: home-page
Dynamic: license-file
Dynamic: requires-python
